{
  "id": "crSUMUn_fbcOVkwkJUshp",
  "name": "BeneListFT_BeneVlist_DS_Trig",
  "projectId": "63ef72a290c5800428f84dd9",
  "services": [
    {
      "type": "DATASTORAGE",
      "command": {
        "type": "3",
        "attributes": {
          "serviceName": "Update value against binding key",
          "bindingKey": "beneftlist_bene_data",
          "value": [
            {
              "beneftlist_ownaccount_acctitle_data": "Bakar ALi",
              "beneftlist_ownaccount_accnum_data": "6023589652147852365",
              "beneftlist_ownaccount_bankname_data": "HABIBMETRO"
            },
            {
              "beneftlist_ownaccount_acctitle_data": "Maryam",
              "beneftlist_ownaccount_accnum_data": "03358555478",
              "beneftlist_ownaccount_bankname_data": "MARYAM ALI"
            },
            {
              "beneftlist_ownaccount_acctitle_data": "Faisal",
              "beneftlist_ownaccount_accnum_data": "03258522586",
              "beneftlist_ownaccount_bankname_data": "FAISAL AHMED"
            },
            {
              "beneftlist_ownaccount_acctitle_data": "Babar Raast Id",
              "beneftlist_ownaccount_accnum_data": "03528555478",
              "beneftlist_ownaccount_bankname_data": "BABAR RIZWAN"
            },
            {
              "beneftlist_ownaccount_acctitle_data": "Sara Ali",
              "beneftlist_ownaccount_accnum_data": "6025836521452145632",
              "beneftlist_ownaccount_bankname_data": "FAYSAL BANK"
            }
          ],
          "contentType": "array",
          "totalcolumns": "3"
        }
      }
    }
  ],
  "gitBranchName": "master",
  "_id": "rDVHAVfeQb6G07JrynJv5",
  "updatedAt": "5/3/2023",
  "createdAt": "5/3/2023",
  "createdBy": "shaikhahmedraza",
  "updatedBy": "shaikhahmedraza"
}
