{
  "id": "JjtpmKWQy4lNlPNrGoceC",
  "projectId": "63ef72a290c5800428f84dd9",
  "name": "HideBalance_Amount_Hide",
  "status": "ACTIVE",
  "services": [
    {
      "type": "UI",
      "command": {
        "type": "34",
        "attributes": {
          "serviceName": "List view toggle visibility",
          "screenId": "M53iHtGCx-9kxK_qBwY19",
          "component": [
            { "id": "PAAOnNa_9nGG0_zLejraZ", "name": "Text view" },
            { "id": "G4PUCS2goGe6bgW0jGyOf", "name": "Text view" },
            { "id": "bUVl59mZL0imGk9AMhh8I", "name": "Text view" },
            {
              "id": "9j6DkctZjoELkmPy-Myiq",
              "name": "HMB_Dash_Account_Hlist_ShowHideBalance_Eye_Icon"
            },
            {
              "id": "d17Hds8lf222hOe6FOdmw",
              "name": "HMB_Dash_Account_Hlist_ShowHideBalance_HideShowBalance_Text"
            }
          ],
          "componentId": [
            "PAAOnNa_9nGG0_zLejraZ",
            "G4PUCS2goGe6bgW0jGyOf",
            "bUVl59mZL0imGk9AMhh8I",
            "9j6DkctZjoELkmPy-Myiq",
            "d17Hds8lf222hOe6FOdmw"
          ],
          "visibility": false
        },
        "returns": []
      }
    }
  ],
  "gitBranchName": "master",
  "csrf": "0.1ln017arjcqqWPOjkPBAsxBHk8xiD0jY",
  "_id": "epZId68aqD2Rfzm42iL7q",
  "updatedAt": "9/4/2023",
  "createdAt": "9/4/2023",
  "createdBy": "shaikhahmedraza",
  "updatedBy": "shaikhahmedraza",
  "old_name": "HideBalance_Amount_Hide"
}
