{
  "id": "nZs4efl0s4-eOFW_KX-AT",
  "name": "navigate to donation screen",
  "projectId": "63ef72a290c5800428f84dd9",
  "services": [
    {
      "type": "NAVIGATION",
      "command": {
        "type": "2",
        "attributes": {
          "serviceName": "Navigate with back stack",
          "id": "PQrLhMwr8pQZg6YrI6Mrqp",
          "type":"push"
        }
      }
    }
  ],
  "gitBranchName": "master",
  "csrf": "0.ok329gkb0rht-pGWAYAWaiuNhT2frVb-",
  "_id": "tBWNx0VIz_ga-oZBUG2nZ",
  "updatedAt": "10/3/2023",
  "createdAt": "10/3/2023",
  "createdBy": "ammarahmed",
  "updatedBy": "ammarahmed"
}
