{
  "id": "71p1l_ygTuJV7sQIG1t5r",
  "name": "Register_IdType_Btmsht",
  "projectId": "63ef72a290c5800428f84dd9",
  "services": [
    {
      "type": "NAVIGATION",
      "command": {
        "type": "3",
        "attributes": {
          "serviceName": "Show bottomsheet",
          "values": [],
          "componentId": "KU71qVeAh69Y0XVNiAUhx"
        }
      }
    }
  ],
  "gitBranchName": "master",
  "_id": "ZDFkMVKXElAxHBEL9XsbT",
  "updatedAt": "3/8/2023",
  "createdAt": "3/8/2023",
  "createdBy": "shaikhahmedraza",
  "updatedBy": "shaikhahmedraza"
}
