[
  {
    "id": "-rl3-UFFa6rWpSb3is62n",
    "name": "HMB_Profile_Screen",
    "icon": "FaGripHorizontal",
    "path": "0",
    "attributes": {
      "name": "HMB_Profile_Screen",
      "layoutProperties": {
        "orientation": "vertical",
        "layout_width": "match_parent",
        "layout_height": "wrap_content",
        "statusBarColor": "#093959",
        "background": "#F8F8F8",
        "navBarColor": "#093959",
        "hideNavbar": true,
        "cornerRadius": [0, 0, 0, 0]
      },
      "componentId": [
        "VzXMaPCd_RwBAUxmdBQcM",
        "PXBDuYWZCD3-g8PSm1VFM",
        "kS1L6UGuDjfysPKxldFgq",
        "lCpNKoqaVVAODn1f5ibGR",
        "5z8LPqupRgEPPJHoMOR2A",
        "c9j-VzOytzLcv69i9t_Vr"
      ]
    },
    "group": "Layout",
    "type": "CONSTRAINT",
    "status": "ACTIVE",
    "updatedAt": "2/27/2023",
    "createdAt": "2/27/2023",
    "events": [],
    "order": 1,
    "version": "1.0.0",
    "isLatest": true,
    "component": { "content": "Constraint Layout", "type": "CONSTRAINT" },
    "gridProps": [
      {
        "id": "VzXMaPCd_RwBAUxmdBQcM",
        "status": "ACTIVE",
        "_id": "61decd8e077814a0f374d9fc",
        "name": "Profile_Bg",
        "attributes": {
          "name": "Profile_Bg",
          "layoutProperties": {
            "layout_width": "match_parent",
            "layout_height": "match_parent",
            "cornerRadius": [0, 0, 0, 0],
            "src": "KN6esKJCZLCTf-oNIAaF6",
            "srcTemp": {
              "createdBy": "shaikhahmedraza",
              "_id": "63f8590abf8c983b9cc00fa4",
              "name": "Dash_background_Img3.png",
              "type": "png",
              "projectId": "63ef72a290c5800428f84dd9",
              "id": "KN6esKJCZLCTf-oNIAaF6",
              "gitBranchName": "master",
              "folderType": "xxxhdpi",
              "platform": "Android",
              "url": "Dash_background_Img3.png",
              "canvasUrl": "Android/drawable-xxxhdpi/Dash_background_Img3.png",
              "createdAt": "2023-02-24T06:28:26.626Z",
              "updatedAt": "2023-02-24T06:28:26.626Z",
              "__v": 0,
              "uri": "Dash_background_Img3.png"
            },
            "leftToLeftOf": "-rl3-UFFa6rWpSb3is62n",
            "rightToRightOf": "-rl3-UFFa6rWpSb3is62n",
            "topToTopOf": "-rl3-UFFa6rWpSb3is62n",
            "bottomToBottomOf": "-rl3-UFFa6rWpSb3is62n"
          },
          "contentType": 2
        },
        "icon": "FaRegImage",
        "group": "Form",
        "type": "sidebarItem",
        "updatedAt": "23-Aug-2021",
        "createdAt": "23-Aug-2021",
        "order": 20,
        "version": "1.0.0",
        "isLatest": true,
        "projectType": "mobile",
        "component": { "content": "Image view", "type": "IMAGEVIEW" },
        "path": "0-0",
        "edit": true,
        "events": []
      },
      {
        "id": "PXBDuYWZCD3-g8PSm1VFM",
        "status": "ACTIVE",
        "_id": "61decd8e077814a0f374d9fc",
        "name": "Profile_Back_Icon",
        "attributes": {
          "name": "Profile_Back_Icon",
          "layoutProperties": {
            "layout_width": "10",
            "layout_height": "18",
            "cornerRadius": [0, 0, 0, 0],
            "src": "1d8bk13Zt-VqOzmOlGNvr",
            "srcTemp": {
              "createdBy": "shaikhahmedraza",
              "_id": "63f8597bbf8c983b9cc00fd5",
              "name": "HMB_Back.png",
              "type": "png",
              "projectId": "63ef72a290c5800428f84dd9",
              "id": "1d8bk13Zt-VqOzmOlGNvr",
              "gitBranchName": "master",
              "folderType": "xxxhdpi",
              "platform": "Android",
              "url": "HMB_Back.png",
              "canvasUrl": "Android/drawable-xxxhdpi/HMB_Back.png",
              "createdAt": "2023-02-24T06:30:19.246Z",
              "updatedAt": "2023-02-24T06:30:19.246Z",
              "__v": 0,
              "uri": "HMB_Back.png"
            },
            "leftToLeftOf": "VzXMaPCd_RwBAUxmdBQcM",
            "topToTopOf": "VzXMaPCd_RwBAUxmdBQcM",
            "layout_marginLeft": 20,
            "layout_marginTop": 40
          },
          "contentType": 2
        },
        "icon": "FaRegImage",
        "group": "Form",
        "type": "sidebarItem",
        "updatedAt": "23-Aug-2021",
        "createdAt": "23-Aug-2021",
        "order": 20,
        "version": "1.0.0",
        "isLatest": true,
        "projectType": "mobile",
        "component": { "content": "Image view", "type": "IMAGEVIEW" },
        "path": "0-1"
      },
      {
        "id": "kS1L6UGuDjfysPKxldFgq",
        "status": "ACTIVE",
        "_id": "61decd8e077814a0f374d9fc",
        "name": "Profile_User_Icon",
        "attributes": {
          "name": "Profile_User_Icon",
          "layoutProperties": {
            "layout_width": "45",
            "layout_height": "45",
            "cornerRadius": [0, 0, 0, 0],
            "src": "uREVADSKaPZNDKGUqrzce",
            "srcTemp": {
              "createdBy": "shaikhahmedraza",
              "_id": "63f859ddbf8c983b9cc00ff8",
              "name": "Dashboard_Profile_Icon.png",
              "type": "png",
              "projectId": "63ef72a290c5800428f84dd9",
              "id": "uREVADSKaPZNDKGUqrzce",
              "gitBranchName": "master",
              "folderType": "xxxhdpi",
              "platform": "Android",
              "url": "Dashboard_Profile_Icon.png",
              "canvasUrl": "Android/drawable-xxxhdpi/Dashboard_Profile_Icon.png",
              "createdAt": "2023-02-24T06:31:57.507Z",
              "updatedAt": "2023-02-24T06:31:57.507Z",
              "__v": 0,
              "uri": "Dashboard_Profile_Icon.png"
            },
            "leftToLeftOf": "VzXMaPCd_RwBAUxmdBQcM",
            "rightToRightOf": "VzXMaPCd_RwBAUxmdBQcM",
            "topToTopOf": "VzXMaPCd_RwBAUxmdBQcM",
            "layout_marginTop": 30
          },
          "contentType": 2
        },
        "icon": "FaRegImage",
        "group": "Form",
        "type": "sidebarItem",
        "updatedAt": "23-Aug-2021",
        "createdAt": "23-Aug-2021",
        "order": 20,
        "version": "1.0.0",
        "isLatest": true,
        "projectType": "mobile",
        "component": { "content": "Image view", "type": "IMAGEVIEW" },
        "path": "0-2"
      },
      {
        "id": "lCpNKoqaVVAODn1f5ibGR",
        "status": "ACTIVE",
        "_id": "61decd8e077814a0f374d9fc",
        "name": "Profile_MainMenu_Icon",
        "attributes": {
          "name": "Profile_MainMenu_Icon",
          "layoutProperties": {
            "layout_width": "25",
            "layout_height": "39",
            "cornerRadius": [0, 0, 0, 0],
            "src": "InZTBEkHr_JeudX2e-WEQ",
            "srcTemp": {
              "createdBy": "shaikhahmedraza",
              "_id": "63f85a2ebf8c983b9cc0101b",
              "name": "HMB_Home_main_Icon.png",
              "type": "png",
              "projectId": "63ef72a290c5800428f84dd9",
              "id": "InZTBEkHr_JeudX2e-WEQ",
              "gitBranchName": "master",
              "folderType": "xxxhdpi",
              "platform": "Android",
              "url": "HMB_Home_main_Icon.png",
              "canvasUrl": "Android/drawable-xxxhdpi/HMB_Home_main_Icon.png",
              "createdAt": "2023-02-24T06:33:18.401Z",
              "updatedAt": "2023-02-24T06:33:18.401Z",
              "__v": 0,
              "uri": "HMB_Home_main_Icon.png"
            },
            "rightToRightOf": "VzXMaPCd_RwBAUxmdBQcM",
            "topToTopOf": "VzXMaPCd_RwBAUxmdBQcM",
            "layout_marginTop": 30,
            "layout_marginRight": 20
          },
          "contentType": 2
        },
        "icon": "FaRegImage",
        "group": "Form",
        "type": "sidebarItem",
        "updatedAt": "23-Aug-2021",
        "createdAt": "23-Aug-2021",
        "order": 20,
        "version": "1.0.0",
        "isLatest": true,
        "projectType": "mobile",
        "component": { "content": "Image view", "type": "IMAGEVIEW" },
        "path": "0-3"
      },
      {
        "id": "5z8LPqupRgEPPJHoMOR2A",
        "status": "ACTIVE",
        "_id": "61dec5ad077814a0f374d9f3",
        "name": "Text view",
        "attributes": {
          "name": "Profile_User_Head_Text",
          "layoutProperties": {
            "textSize": 16,
            "layout_width": "wrap_content",
            "layout_height": "40",
            "textColor": "#ffffff",
            "text": "Shaikh Ahmed Raza",
            "cornerRadius": [0, 0, 0, 0],
            "leftToLeftOf": "VzXMaPCd_RwBAUxmdBQcM",
            "rightToRightOf": "VzXMaPCd_RwBAUxmdBQcM",
            "topToBottomOf": "kS1L6UGuDjfysPKxldFgq",
            "layout_marginTop": null,
            "textStyle": "regular",
            "fontName": "CircularStd",
            "textAlignment": "center"
          }
        },
        "icon": "FaTextWidth",
        "group": "Form",
        "type": "sidebarItem",
        "updatedAt": "23-Aug-2021",
        "createdAt": "23-Aug-2021",
        "order": 20,
        "version": "1.0.0",
        "isLatest": true,
        "projectType": "mobile",
        "component": { "content": "Text view", "type": "TEXTVIEW" },
        "events": [],
        "path": "0-4"
      },
      {
        "id": "c9j-VzOytzLcv69i9t_Vr",
        "status": "ACTIVE",
        "_id": "61dec691077814a0f374d9f4",
        "name": "Profile_Main_White_View",
        "attributes": {
          "name": "Profile_Main_White_View",
          "layoutProperties": {
            "name": "View",
            "layout_width": "match_parent",
            "layout_height": "match_parent",
            "borderWidth": 0,
            "cornerRadius": [0, 0, 0, 0],
            "background": "#FFFFFF",
            "leftToLeftOf": "VzXMaPCd_RwBAUxmdBQcM",
            "rightToRightOf": "VzXMaPCd_RwBAUxmdBQcM",
            "topToBottomOf": "5z8LPqupRgEPPJHoMOR2A",
            "bottomToBottomOf": "VzXMaPCd_RwBAUxmdBQcM",
            "layout_marginTop": 20,
            "layout_marginLeft": null
          }
        },
        "icon": "FaTabletAlt",
        "group": "Form",
        "type": "sidebarItem",
        "updatedAt": "23-Aug-2021",
        "createdAt": "23-Aug-2021",
        "order": 20,
        "version": "1.0.0",
        "isLatest": true,
        "projectType": "mobile",
        "component": { "content": "View", "type": "VIEW" },
        "events": [],
        "path": "0-5"
      }
    ],
    "subType": "screen",
    "layout": [
      {
        "id": "-rl3-UFFa6rWpSb3is62n",
        "name": "HMB_Profile_Screen",
        "icon": "FaGripHorizontal",
        "path": "0",
        "attributes": {
          "name": "HMB_Profile_Screen",
          "layoutProperties": {
            "orientation": "vertical",
            "layout_width": "match_parent",
            "layout_height": "wrap_content",
            "statusBarColor": "#093959",
            "background": "#F8F8F8",
            "navBarColor": "#093959",
            "hideNavbar": true,
            "cornerRadius": [0, 0, 0, 0]
          },
          "componentId": []
        },
        "group": "Layout",
        "type": "CONSTRAINT",
        "status": "ACTIVE",
        "updatedAt": "2021-09-23T15:17:45.489Z",
        "createdAt": "2021-08-24T06:05:50.559Z",
        "events": [],
        "order": 1,
        "version": "1.0.0",
        "isLatest": true,
        "component": { "content": "Constraint Layout", "type": "CONSTRAINT" },
        "gridProps": [
          {
            "id": "VzXMaPCd_RwBAUxmdBQcM",
            "status": "ACTIVE",
            "_id": "61decd8e077814a0f374d9fc",
            "name": "Profile_Bg",
            "attributes": {
              "name": "Profile_Bg",
              "layoutProperties": {
                "layout_width": "match_parent",
                "layout_height": "match_parent",
                "cornerRadius": [0, 0, 0, 0],
                "src": "KN6esKJCZLCTf-oNIAaF6",
                "srcTemp": {
                  "createdBy": "shaikhahmedraza",
                  "_id": "63f8590abf8c983b9cc00fa4",
                  "name": "Dash_background_Img3.png",
                  "type": "png",
                  "projectId": "63ef72a290c5800428f84dd9",
                  "id": "KN6esKJCZLCTf-oNIAaF6",
                  "gitBranchName": "master",
                  "folderType": "xxxhdpi",
                  "platform": "Android",
                  "url": "Dash_background_Img3.png",
                  "canvasUrl": "Android/drawable-xxxhdpi/Dash_background_Img3.png",
                  "createdAt": "2023-02-24T06:28:26.626Z",
                  "updatedAt": "2023-02-24T06:28:26.626Z",
                  "__v": 0,
                  "uri": "Dash_background_Img3.png"
                },
                "leftToLeftOf": "-rl3-UFFa6rWpSb3is62n",
                "rightToRightOf": "-rl3-UFFa6rWpSb3is62n",
                "topToTopOf": "-rl3-UFFa6rWpSb3is62n",
                "bottomToBottomOf": "-rl3-UFFa6rWpSb3is62n"
              },
              "contentType": 2
            },
            "icon": "FaRegImage",
            "group": "Form",
            "type": "sidebarItem",
            "updatedAt": "23-Aug-2021",
            "createdAt": "23-Aug-2021",
            "order": 20,
            "version": "1.0.0",
            "isLatest": true,
            "projectType": "mobile",
            "component": { "content": "Image view", "type": "IMAGEVIEW" },
            "path": "0-0",
            "edit": true,
            "events": []
          },
          {
            "id": "PXBDuYWZCD3-g8PSm1VFM",
            "status": "ACTIVE",
            "_id": "61decd8e077814a0f374d9fc",
            "name": "Profile_Back_Icon",
            "attributes": {
              "name": "Profile_Back_Icon",
              "layoutProperties": {
                "layout_width": "10",
                "layout_height": "18",
                "cornerRadius": [0, 0, 0, 0],
                "src": "1d8bk13Zt-VqOzmOlGNvr",
                "srcTemp": {
                  "createdBy": "shaikhahmedraza",
                  "_id": "63f8597bbf8c983b9cc00fd5",
                  "name": "HMB_Back.png",
                  "type": "png",
                  "projectId": "63ef72a290c5800428f84dd9",
                  "id": "1d8bk13Zt-VqOzmOlGNvr",
                  "gitBranchName": "master",
                  "folderType": "xxxhdpi",
                  "platform": "Android",
                  "url": "HMB_Back.png",
                  "canvasUrl": "Android/drawable-xxxhdpi/HMB_Back.png",
                  "createdAt": "2023-02-24T06:30:19.246Z",
                  "updatedAt": "2023-02-24T06:30:19.246Z",
                  "__v": 0,
                  "uri": "HMB_Back.png"
                },
                "leftToLeftOf": "VzXMaPCd_RwBAUxmdBQcM",
                "topToTopOf": "VzXMaPCd_RwBAUxmdBQcM",
                "layout_marginLeft": 20,
                "layout_marginTop": 40
              },
              "contentType": 2
            },
            "icon": "FaRegImage",
            "group": "Form",
            "type": "sidebarItem",
            "updatedAt": "23-Aug-2021",
            "createdAt": "23-Aug-2021",
            "order": 20,
            "version": "1.0.0",
            "isLatest": true,
            "projectType": "mobile",
            "component": { "content": "Image view", "type": "IMAGEVIEW" },
            "path": "0-1"
          },
          {
            "id": "kS1L6UGuDjfysPKxldFgq",
            "status": "ACTIVE",
            "_id": "61decd8e077814a0f374d9fc",
            "name": "Profile_User_Icon",
            "attributes": {
              "name": "Profile_User_Icon",
              "layoutProperties": {
                "layout_width": "45",
                "layout_height": "45",
                "cornerRadius": [0, 0, 0, 0],
                "src": "uREVADSKaPZNDKGUqrzce",
                "srcTemp": {
                  "createdBy": "shaikhahmedraza",
                  "_id": "63f859ddbf8c983b9cc00ff8",
                  "name": "Dashboard_Profile_Icon.png",
                  "type": "png",
                  "projectId": "63ef72a290c5800428f84dd9",
                  "id": "uREVADSKaPZNDKGUqrzce",
                  "gitBranchName": "master",
                  "folderType": "xxxhdpi",
                  "platform": "Android",
                  "url": "Dashboard_Profile_Icon.png",
                  "canvasUrl": "Android/drawable-xxxhdpi/Dashboard_Profile_Icon.png",
                  "createdAt": "2023-02-24T06:31:57.507Z",
                  "updatedAt": "2023-02-24T06:31:57.507Z",
                  "__v": 0,
                  "uri": "Dashboard_Profile_Icon.png"
                },
                "leftToLeftOf": "VzXMaPCd_RwBAUxmdBQcM",
                "rightToRightOf": "VzXMaPCd_RwBAUxmdBQcM",
                "topToTopOf": "VzXMaPCd_RwBAUxmdBQcM",
                "layout_marginTop": 30
              },
              "contentType": 2
            },
            "icon": "FaRegImage",
            "group": "Form",
            "type": "sidebarItem",
            "updatedAt": "23-Aug-2021",
            "createdAt": "23-Aug-2021",
            "order": 20,
            "version": "1.0.0",
            "isLatest": true,
            "projectType": "mobile",
            "component": { "content": "Image view", "type": "IMAGEVIEW" },
            "path": "0-2"
          },
          {
            "id": "lCpNKoqaVVAODn1f5ibGR",
            "status": "ACTIVE",
            "_id": "61decd8e077814a0f374d9fc",
            "name": "Profile_MainMenu_Icon",
            "attributes": {
              "name": "Profile_MainMenu_Icon",
              "layoutProperties": {
                "layout_width": "25",
                "layout_height": "39",
                "cornerRadius": [0, 0, 0, 0],
                "src": "InZTBEkHr_JeudX2e-WEQ",
                "srcTemp": {
                  "createdBy": "shaikhahmedraza",
                  "_id": "63f85a2ebf8c983b9cc0101b",
                  "name": "HMB_Home_main_Icon.png",
                  "type": "png",
                  "projectId": "63ef72a290c5800428f84dd9",
                  "id": "InZTBEkHr_JeudX2e-WEQ",
                  "gitBranchName": "master",
                  "folderType": "xxxhdpi",
                  "platform": "Android",
                  "url": "HMB_Home_main_Icon.png",
                  "canvasUrl": "Android/drawable-xxxhdpi/HMB_Home_main_Icon.png",
                  "createdAt": "2023-02-24T06:33:18.401Z",
                  "updatedAt": "2023-02-24T06:33:18.401Z",
                  "__v": 0,
                  "uri": "HMB_Home_main_Icon.png"
                },
                "rightToRightOf": "VzXMaPCd_RwBAUxmdBQcM",
                "topToTopOf": "VzXMaPCd_RwBAUxmdBQcM",
                "layout_marginTop": 30,
                "layout_marginRight": 20
              },
              "contentType": 2
            },
            "icon": "FaRegImage",
            "group": "Form",
            "type": "sidebarItem",
            "updatedAt": "23-Aug-2021",
            "createdAt": "23-Aug-2021",
            "order": 20,
            "version": "1.0.0",
            "isLatest": true,
            "projectType": "mobile",
            "component": { "content": "Image view", "type": "IMAGEVIEW" },
            "path": "0-3"
          },
          {
            "id": "5z8LPqupRgEPPJHoMOR2A",
            "status": "ACTIVE",
            "_id": "61dec5ad077814a0f374d9f3",
            "name": "Text view",
            "attributes": {
              "name": "Profile_User_Head_Text",
              "layoutProperties": {
                "textSize": 16,
                "layout_width": "wrap_content",
                "layout_height": "40",
                "textColor": "#ffffff",
                "text": "Shaikh Ahmed Raza",
                "cornerRadius": [0, 0, 0, 0],
                "leftToLeftOf": "VzXMaPCd_RwBAUxmdBQcM",
                "rightToRightOf": "VzXMaPCd_RwBAUxmdBQcM",
                "topToBottomOf": "kS1L6UGuDjfysPKxldFgq",
                "layout_marginTop": null,
                "textStyle": "regular",
                "fontName": "CircularStd",
                "textAlignment": "center"
              }
            },
            "icon": "FaTextWidth",
            "group": "Form",
            "type": "sidebarItem",
            "updatedAt": "23-Aug-2021",
            "createdAt": "23-Aug-2021",
            "order": 20,
            "version": "1.0.0",
            "isLatest": true,
            "projectType": "mobile",
            "component": { "content": "Text view", "type": "TEXTVIEW" },
            "events": [],
            "path": "0-4"
          },
          {
            "id": "c9j-VzOytzLcv69i9t_Vr",
            "status": "ACTIVE",
            "_id": "61dec691077814a0f374d9f4",
            "name": "Profile_Main_White_View",
            "attributes": {
              "name": "Profile_Main_White_View",
              "layoutProperties": {
                "name": "View",
                "layout_width": "match_parent",
                "layout_height": "match_parent",
                "borderWidth": 0,
                "cornerRadius": [0, 0, 0, 0],
                "background": "#FFFFFF",
                "leftToLeftOf": "VzXMaPCd_RwBAUxmdBQcM",
                "rightToRightOf": "VzXMaPCd_RwBAUxmdBQcM",
                "topToBottomOf": "5z8LPqupRgEPPJHoMOR2A",
                "bottomToBottomOf": "VzXMaPCd_RwBAUxmdBQcM",
                "layout_marginTop": 20,
                "layout_marginLeft": null
              }
            },
            "icon": "FaTabletAlt",
            "group": "Form",
            "type": "sidebarItem",
            "updatedAt": "23-Aug-2021",
            "createdAt": "23-Aug-2021",
            "order": 20,
            "version": "1.0.0",
            "isLatest": true,
            "projectType": "mobile",
            "component": { "content": "View", "type": "VIEW" },
            "events": [],
            "path": "0-5"
          }
        ],
        "subType": "screen"
      }
    ],
    "projectId": "63ef72a290c5800428f84dd9",
    "gitBranchName": "master",
    "_id": "-rl3-UFFa6rWpSb3is62n",
    "createdBy": "shaikhahmedraza",
    "updatedTimestamp": "0000-00-00T00:00:00+00:00"
  },
  {
    "id": "VzXMaPCd_RwBAUxmdBQcM",
    "status": "ACTIVE",
    "name": "Profile_Bg",
    "attributes": {
      "name": "Profile_Bg",
      "layoutProperties": {
        "layout_width": "match_parent",
        "layout_height": "match_parent",
        "cornerRadius": [0, 0, 0, 0],
        "src": "KN6esKJCZLCTf-oNIAaF6",
        "srcTemp": {
          "createdBy": "shaikhahmedraza",
          "_id": "63f8590abf8c983b9cc00fa4",
          "name": "Dash_background_Img3.png",
          "type": "png",
          "projectId": "63ef72a290c5800428f84dd9",
          "id": "KN6esKJCZLCTf-oNIAaF6",
          "gitBranchName": "master",
          "folderType": "xxxhdpi",
          "platform": "Android",
          "url": "Dash_background_Img3.png",
          "canvasUrl": "Android/drawable-xxxhdpi/Dash_background_Img3.png",
          "createdAt": "2023-02-24T06:28:26.626Z",
          "updatedAt": "2023-02-24T06:28:26.626Z",
          "__v": 0,
          "uri": "Dash_background_Img3.png"
        },
        "leftToLeftOf": "-rl3-UFFa6rWpSb3is62n",
        "rightToRightOf": "-rl3-UFFa6rWpSb3is62n",
        "topToTopOf": "-rl3-UFFa6rWpSb3is62n",
        "bottomToBottomOf": "-rl3-UFFa6rWpSb3is62n"
      },
      "contentType": 2
    },
    "icon": "FaRegImage",
    "group": "Form",
    "type": "IMAGEVIEW",
    "updatedAt": "23-Aug-2021",
    "createdAt": "23-Aug-2021",
    "order": 20,
    "version": "1.0.0",
    "isLatest": true,
    "projectType": "mobile",
    "component": { "content": "Image view", "type": "IMAGEVIEW" },
    "path": "0-0",
    "edit": true,
    "events": [],
    "subType": "component",
    "projectId": "63ef72a290c5800428f84dd9",
    "gitBranchName": "master",
    "updatedTimestamp": "0000-00-00T00:00:00+00:00"
  },
  {
    "id": "PXBDuYWZCD3-g8PSm1VFM",
    "status": "ACTIVE",
    "name": "Profile_Back_Icon",
    "attributes": {
      "name": "Profile_Back_Icon",
      "layoutProperties": {
        "layout_width": "10",
        "layout_height": "18",
        "cornerRadius": [0, 0, 0, 0],
        "src": "1d8bk13Zt-VqOzmOlGNvr",
        "srcTemp": {
          "createdBy": "shaikhahmedraza",
          "_id": "63f8597bbf8c983b9cc00fd5",
          "name": "HMB_Back.png",
          "type": "png",
          "projectId": "63ef72a290c5800428f84dd9",
          "id": "1d8bk13Zt-VqOzmOlGNvr",
          "gitBranchName": "master",
          "folderType": "xxxhdpi",
          "platform": "Android",
          "url": "HMB_Back.png",
          "canvasUrl": "Android/drawable-xxxhdpi/HMB_Back.png",
          "createdAt": "2023-02-24T06:30:19.246Z",
          "updatedAt": "2023-02-24T06:30:19.246Z",
          "__v": 0,
          "uri": "HMB_Back.png"
        },
        "leftToLeftOf": "VzXMaPCd_RwBAUxmdBQcM",
        "topToTopOf": "VzXMaPCd_RwBAUxmdBQcM",
        "layout_marginLeft": 20,
        "layout_marginTop": 40
      },
      "contentType": 2
    },
    "icon": "FaRegImage",
    "group": "Form",
    "type": "IMAGEVIEW",
    "updatedAt": "23-Aug-2021",
    "createdAt": "23-Aug-2021",
    "order": 20,
    "version": "1.0.0",
    "isLatest": true,
    "projectType": "mobile",
    "component": { "content": "Image view", "type": "IMAGEVIEW" },
    "path": "0-1",
    "subType": "component",
    "projectId": "63ef72a290c5800428f84dd9",
    "gitBranchName": "master",
    "updatedTimestamp": "0000-00-00T00:00:00+00:00"
  },
  {
    "id": "kS1L6UGuDjfysPKxldFgq",
    "status": "ACTIVE",
    "name": "Profile_User_Icon",
    "attributes": {
      "name": "Profile_User_Icon",
      "layoutProperties": {
        "layout_width": "45",
        "layout_height": "45",
        "cornerRadius": [0, 0, 0, 0],
        "src": "uREVADSKaPZNDKGUqrzce",
        "srcTemp": {
          "createdBy": "shaikhahmedraza",
          "_id": "63f859ddbf8c983b9cc00ff8",
          "name": "Dashboard_Profile_Icon.png",
          "type": "png",
          "projectId": "63ef72a290c5800428f84dd9",
          "id": "uREVADSKaPZNDKGUqrzce",
          "gitBranchName": "master",
          "folderType": "xxxhdpi",
          "platform": "Android",
          "url": "Dashboard_Profile_Icon.png",
          "canvasUrl": "Android/drawable-xxxhdpi/Dashboard_Profile_Icon.png",
          "createdAt": "2023-02-24T06:31:57.507Z",
          "updatedAt": "2023-02-24T06:31:57.507Z",
          "__v": 0,
          "uri": "Dashboard_Profile_Icon.png"
        },
        "leftToLeftOf": "VzXMaPCd_RwBAUxmdBQcM",
        "rightToRightOf": "VzXMaPCd_RwBAUxmdBQcM",
        "topToTopOf": "VzXMaPCd_RwBAUxmdBQcM",
        "layout_marginTop": 30
      },
      "contentType": 2
    },
    "icon": "FaRegImage",
    "group": "Form",
    "type": "IMAGEVIEW",
    "updatedAt": "23-Aug-2021",
    "createdAt": "23-Aug-2021",
    "order": 20,
    "version": "1.0.0",
    "isLatest": true,
    "projectType": "mobile",
    "component": { "content": "Image view", "type": "IMAGEVIEW" },
    "path": "0-2",
    "subType": "component",
    "projectId": "63ef72a290c5800428f84dd9",
    "gitBranchName": "master",
    "updatedTimestamp": "0000-00-00T00:00:00+00:00"
  },
  {
    "id": "lCpNKoqaVVAODn1f5ibGR",
    "status": "ACTIVE",
    "name": "Profile_MainMenu_Icon",
    "attributes": {
      "name": "Profile_MainMenu_Icon",
      "layoutProperties": {
        "layout_width": "25",
        "layout_height": "39",
        "cornerRadius": [0, 0, 0, 0],
        "src": "InZTBEkHr_JeudX2e-WEQ",
        "srcTemp": {
          "createdBy": "shaikhahmedraza",
          "_id": "63f85a2ebf8c983b9cc0101b",
          "name": "HMB_Home_main_Icon.png",
          "type": "png",
          "projectId": "63ef72a290c5800428f84dd9",
          "id": "InZTBEkHr_JeudX2e-WEQ",
          "gitBranchName": "master",
          "folderType": "xxxhdpi",
          "platform": "Android",
          "url": "HMB_Home_main_Icon.png",
          "canvasUrl": "Android/drawable-xxxhdpi/HMB_Home_main_Icon.png",
          "createdAt": "2023-02-24T06:33:18.401Z",
          "updatedAt": "2023-02-24T06:33:18.401Z",
          "__v": 0,
          "uri": "HMB_Home_main_Icon.png"
        },
        "rightToRightOf": "VzXMaPCd_RwBAUxmdBQcM",
        "topToTopOf": "VzXMaPCd_RwBAUxmdBQcM",
        "layout_marginTop": 30,
        "layout_marginRight": 20
      },
      "contentType": 2
    },
    "icon": "FaRegImage",
    "group": "Form",
    "type": "IMAGEVIEW",
    "updatedAt": "23-Aug-2021",
    "createdAt": "23-Aug-2021",
    "order": 20,
    "version": "1.0.0",
    "isLatest": true,
    "projectType": "mobile",
    "component": { "content": "Image view", "type": "IMAGEVIEW" },
    "path": "0-3",
    "subType": "component",
    "projectId": "63ef72a290c5800428f84dd9",
    "gitBranchName": "master",
    "updatedTimestamp": "0000-00-00T00:00:00+00:00"
  },
  {
    "id": "5z8LPqupRgEPPJHoMOR2A",
    "status": "ACTIVE",
    "name": "Text view",
    "attributes": {
      "name": "Profile_User_Head_Text",
      "layoutProperties": {
        "textSize": 16,
        "layout_width": "wrap_content",
        "layout_height": "40",
        "textColor": "#ffffff",
        "text": "Shaikh Ahmed Raza",
        "cornerRadius": [0, 0, 0, 0],
        "leftToLeftOf": "VzXMaPCd_RwBAUxmdBQcM",
        "rightToRightOf": "VzXMaPCd_RwBAUxmdBQcM",
        "topToBottomOf": "kS1L6UGuDjfysPKxldFgq",
        "layout_marginTop": null,
        "textStyle": "regular",
        "fontName": "CircularStd",
        "textAlignment": "center"
      }
    },
    "icon": "FaTextWidth",
    "group": "Form",
    "type": "TEXTVIEW",
    "updatedAt": "23-Aug-2021",
    "createdAt": "23-Aug-2021",
    "order": 20,
    "version": "1.0.0",
    "isLatest": true,
    "projectType": "mobile",
    "component": { "content": "Text view", "type": "TEXTVIEW" },
    "events": [],
    "path": "0-4",
    "subType": "component",
    "projectId": "63ef72a290c5800428f84dd9",
    "gitBranchName": "master",
    "updatedTimestamp": "0000-00-00T00:00:00+00:00"
  },
  {
    "id": "c9j-VzOytzLcv69i9t_Vr",
    "status": "ACTIVE",
    "name": "Profile_Main_White_View",
    "attributes": {
      "name": "Profile_Main_White_View",
      "layoutProperties": {
        "name": "View",
        "layout_width": "match_parent",
        "layout_height": "match_parent",
        "borderWidth": 0,
        "cornerRadius": [0, 0, 0, 0],
        "background": "#FFFFFF",
        "leftToLeftOf": "VzXMaPCd_RwBAUxmdBQcM",
        "rightToRightOf": "VzXMaPCd_RwBAUxmdBQcM",
        "topToBottomOf": "5z8LPqupRgEPPJHoMOR2A",
        "bottomToBottomOf": "VzXMaPCd_RwBAUxmdBQcM",
        "layout_marginTop": 20,
        "layout_marginLeft": null
      }
    },
    "icon": "FaTabletAlt",
    "group": "Form",
    "type": "VIEW",
    "updatedAt": "23-Aug-2021",
    "createdAt": "23-Aug-2021",
    "order": 20,
    "version": "1.0.0",
    "isLatest": true,
    "projectType": "mobile",
    "component": { "content": "View", "type": "VIEW" },
    "events": [],
    "path": "0-5",
    "subType": "component",
    "projectId": "63ef72a290c5800428f84dd9",
    "gitBranchName": "master",
    "updatedTimestamp": "0000-00-00T00:00:00+00:00"
  }
]
